__init__.py
fakefaceinf.py
fakeface_detector-0.0.2.dist-info/LICENSE.txt
fakeface_detector-0.0.2.dist-info/METADATA
fakeface_detector-0.0.2.dist-info/WHEEL
fakeface_detector-0.0.2.dist-info/top_level.txt
fakeface_detector-0.0.2.dist-info/RECORD
