Metadata-Version: 2.1
Name: fakeface_detector
Version: 0.0.2
Summary: A python module to detect face liveness.
Author-email: Fahd Abrahams <fahd@perpendicular.web.za>
Project-URL: Homepage, https://github.com/perpendicularai/imageclassification/tree/main
Project-URL: Issues, https://github.com/perpendicularai/imageclassification/issues
Classifier: Programming Language :: Python :: 3
Classifier: License :: OSI Approved :: MIT License
Classifier: Operating System :: OS Independent
Requires-Python: >=3.8
License-File: LICENSE.txt
